nasrparse/__init__.py
nasrparse/main.py
nasrparse/filenames/__init__.py
nasrparse/filenames/apt.py
nasrparse/filenames/arb.py
nasrparse/filenames/atc.py
nasrparse/filenames/awos.py
nasrparse/filenames/awy.py
nasrparse/filenames/cdr.py
nasrparse/filenames/cls.py
nasrparse/filenames/com.py
nasrparse/filenames/dp.py
nasrparse/filenames/fix.py
nasrparse/filenames/frq.py
nasrparse/filenames/fss.py
nasrparse/filenames/hpf.py
nasrparse/filenames/ils.py
nasrparse/filenames/lid.py
nasrparse/filenames/maa.py
nasrparse/filenames/mil.py
nasrparse/filenames/mtr.py
nasrparse/filenames/nav.py
nasrparse/filenames/pfr.py
nasrparse/filenames/pja.py
nasrparse/filenames/rdr.py
nasrparse/filenames/star.py
nasrparse/filenames/wxl.py
nasrparse/functions/__init__.py
nasrparse/functions/csv.py
nasrparse/functions/files.py
nasrparse/functions/record.py
nasrparse/functions/sql.py
nasrparse/records/__init__.py
nasrparse/records/apts.py
nasrparse/records/arbs.py
nasrparse/records/atcs.py
nasrparse/records/awoss.py
nasrparse/records/awys.py
nasrparse/records/cdrs.py
nasrparse/records/clss.py
nasrparse/records/coms.py
nasrparse/records/dps.py
nasrparse/records/fixs.py
nasrparse/records/frqs.py
nasrparse/records/fsss.py
nasrparse/records/hpfs.py
nasrparse/records/ilss.py
nasrparse/records/lids.py
nasrparse/records/maas.py
nasrparse/records/mils.py
nasrparse/records/mtrs.py
nasrparse/records/navs.py
nasrparse/records/pfrs.py
nasrparse/records/pjas.py
nasrparse/records/rdrs.py
nasrparse/records/stars.py
nasrparse/records/table_base.py
nasrparse/records/wxls.py
nasrparse/records/apt/__init__.py
nasrparse/records/apt/_base.py
nasrparse/records/apt/apt_ars.py
nasrparse/records/apt/apt_att.py
nasrparse/records/apt/apt_base.py
nasrparse/records/apt/apt_con.py
nasrparse/records/apt/apt_rmk.py
nasrparse/records/apt/apt_rwy.py
nasrparse/records/apt/apt_rwy_end.py
nasrparse/records/arb/__init__.py
nasrparse/records/arb/_base.py
nasrparse/records/arb/arb_base.py
nasrparse/records/arb/arb_seg.py
nasrparse-1.1.0.dist-info/licenses/LICENSE
nasrparse-1.1.0.dist-info/METADATA
nasrparse-1.1.0.dist-info/WHEEL
nasrparse-1.1.0.dist-info/top_level.txt
nasrparse-1.1.0.dist-info/RECORD
