Metadata-Version: 2.4
Name: nasrparse
Version: 1.1.0
Summary: A python parser for the FAA NASR
Author: misterrodg
License-Expression: GPL-3.0-only
Project-URL: Homepage, https://github.com/misterrodg/nasrparse
Project-URL: Bug Tracker, https://github.com/misterrodg/nasrparse/issues
Classifier: Programming Language :: Python :: 3
Classifier: Operating System :: OS Independent
Requires-Python: >=3.10
License-File: LICENSE
Dynamic: license-file
